matrix_calculation/__init__.py
Matrix_Sumedha-0.1.dist-info/LICENCE.txt
Matrix_Sumedha-0.1.dist-info/METADATA
Matrix_Sumedha-0.1.dist-info/WHEEL
Matrix_Sumedha-0.1.dist-info/top_level.txt
Matrix_Sumedha-0.1.dist-info/RECORD
