Metadata-Version: 2.1
Name: Matrix-Sumedha
Version: 0.1
Summary: A simple package which performs matrix operations like addition of two matrices,their sum, transpose and much more
Author: Sumedha
Author-email: sumedhaghosh83@gmail.com
Classifier: Programming Language :: Python :: 3
Classifier: License :: OSI Approved :: MIT License
Classifier: Operating System :: OS Independent
License-File: LICENCE.txt
